README-cn.md
zmake/__init__.py
zmake/build.py
zmake/cli.py
zmake/core.py
zmake/entity.py
zmake/generator.py
zmake/kconfig.py
zmake/yaml.py
zmake/demo/Kconfig
zmake/demo/test_defconfig
zmake/demo/top.yml
zmake/demo/main/main.c
zmake/demo/main/main.config
zmake/demo/main/main.yml
zmake/demo/main/main2.c
zmake/demo/mod1/mod1.config
zmake/demo/mod1/mod11/mod11.config
zmake/demo/mod1/mod11/mod11.yml
zmake/demo/mod1/mod11/include/mod11/mod11.h
zmake/demo/mod1/mod11/source/mod11.c
zmake/demo/mod1/mod12/mod12.c
zmake/demo/mod1/mod12/mod12.config
zmake/demo/mod1/mod12/mod12.h
zmake/demo/mod1/mod12/mod12.yml
zmake/demo/mod2/mod2.c
zmake/demo/mod2/mod2.config
zmake/demo/mod2/mod2.yml
zmake/demo/mod2/h/mod2.h
zmake/demo/mod2/h/mod2_dbg.h
zmake-0.1.1.dist-info/LICENSE
zmake-0.1.1.dist-info/METADATA
zmake-0.1.1.dist-info/WHEEL
zmake-0.1.1.dist-info/entry_points.txt
zmake-0.1.1.dist-info/top_level.txt
zmake-0.1.1.dist-info/RECORD
