Metadata-Version: 2.1
Name: zmake
Version: 0.1.1
Summary: A Make/ninja-build file generator from Kconfig/YAML config files
Home-page: https://github.com/matthewzu/zmake
Author: Matthew Zu
Author-email: xiaofeng_zu@163.com
License: UNKNOWN
Keywords: make,ninja-build,yaml,kconfig
Platform: UNKNOWN
Classifier: Programming Language :: Python :: 3
Classifier: License :: OSI Approved :: Mozilla Public License 2.0 (MPL 2.0)
Classifier: Operating System :: OS Independent
License-File: LICENSE
Requires-Dist: kconfiglib
Requires-Dist: pyyaml
